easy_ge/__init__.py
easy_ge/entrypoint.py
easy_ge/expectation_manager.py
easy_ge/helpers.py
easy_ge/main.py
easy_ge/templates/checkpoint.tpl
easy_ge/templates/great_expectations.tpl
easy_ge/templates/schema.json
easy_ge-0.1.12.4.dist-info/LICENSE
easy_ge-0.1.12.4.dist-info/METADATA
easy_ge-0.1.12.4.dist-info/WHEEL
easy_ge-0.1.12.4.dist-info/RECORD
